bits/__init__.py
bits/gpgfile/__init__.py
bits_gpgfile-1.0.dist-info/METADATA
bits_gpgfile-1.0.dist-info/RECORD
bits_gpgfile-1.0.dist-info/WHEEL
bits_gpgfile-1.0.dist-info/top_level.txt
